<?xml version="1.0" encoding="UTF-8"?>
<databaseChangeLog xmlns="http://www.liquibase.org/xml/ns/dbchangelog"
                   xmlns:xsi="http://www.w3.org/2001/XMLSchema-instance"
                   xsi:schemaLocation="http://www.liquibase.org/xml/ns/dbchangelog
    http://www.liquibase.org/xml/ns/dbchangelog/dbchangelog-2.0.xsd">

    <changeSet author="chi" id="20170615-add-dataset-map-resource-name-index" runInTransaction="false">
        <preConditions onFail="MARK_RAN">
            <sqlCheck expectedResult="0">
                select count(*) from pg_class where relname = 'dataset_map_resource_name'
            </sqlCheck>
        </preConditions>
        <sql>
            CREATE INDEX CONCURRENTLY dataset_map_resource_name ON dataset_map(resource_name)
        </sql>
        <rollback>
            <dropIndex indexName="dataset_map_resource_name" tableName="dataset_map"/>
        </rollback>
    </changeSet>
</databaseChangeLog>
